DCLS/__init__.py
DCLS/construct/__init__.py
DCLS/construct/modules.py
dcls-0.1.1.dist-info/METADATA
dcls-0.1.1.dist-info/WHEEL
dcls-0.1.1.dist-info/licenses/LICENSE
dcls-0.1.1.dist-info/RECORD
