Metadata-Version: 2.1
Name: DCLS
Version: 0.1.1
Summary: Dilated convolution with learnable spacings, built on PyTorch.
Project-URL: Homepage, https://github.com/K-H-Ismail/Dilated-Convolution-with-Learnable-Spacings-PyTorch
Project-URL: Bug Tracker, https://github.com/K-H-Ismail/Dilated-Convolution-with-Learnable-Spacings-PyTorch/issues
Author-email: Ismail Khalfaoui Hassani <khalfaoui.ismail@hotmail.com>
License-File: LICENSE
Classifier: License :: OSI Approved :: GNU General Public License v3 or later (GPLv3+)
Classifier: Operating System :: OS Independent
Classifier: Programming Language :: Python :: 3.6
Requires-Python: >=3.6
